Metadata-Version: 2.4
Name: llm-fragments-youtube-transcript
Version: 0.1
Summary: Fetch youtube transcripts and convert them into plaintext for llm consumption.
Author: Jack Bowman, Dan Turkel, Simon Willison
License-Expression: MIT
Project-URL: Homepage, https://github.com/jackbow/llm-fragments-youtube-transcript
Project-URL: Changelog, https://github.com/jackbow/llm-fragments-youtube-transcript/releases
Project-URL: Issues, https://github.com/jackbow/llm-fragments-youtube-transcript/issues
Project-URL: CI, https://github.com/jackbow/llm-fragments-youtube-transcript/actions
Requires-Python: >=3.9
License-File: LICENSE
Requires-Dist: llm
Requires-Dist: youtube-transcript-api>=1.1.1
Requires-Dist: yt-dlp
Dynamic: license-file
